algo_lib/__init__.py
algo_lib/search/Search.py
algo_lib/search/__init__.py
algo_lib/search/binary.py
algo_lib/search/linear.py
algo_lib/sort/__init__.py
algo_lib/sort/merge.py
algo_lib-0.0.5.dist-info/LICENSE
algo_lib-0.0.5.dist-info/METADATA
algo_lib-0.0.5.dist-info/WHEEL
algo_lib-0.0.5.dist-info/top_level.txt
algo_lib-0.0.5.dist-info/RECORD
