Metadata-Version: 2.1
Name: algo-lib
Version: 0.0.5
Summary: A small sample package with two search algorithms
Home-page: https://github.com/austinserif/algo-lib
Author: Austin Serif
Author-email: austin@sans-serif.io
License: UNKNOWN
Platform: UNKNOWN
Classifier: Programming Language :: Python :: 3
Classifier: License :: OSI Approved :: MIT License
Classifier: Operating System :: OS Independent
Requires-Python: >=3.6
